cgutils/__init__.py
cgutils/__main__.py
cgutils/commands/__init__.py
cgutils/commands/search_replace.py
cgutils/commands/sequences.py
cgutils-0.1.4.dist-info/DESCRIPTION.rst
cgutils-0.1.4.dist-info/METADATA
cgutils-0.1.4.dist-info/RECORD
cgutils-0.1.4.dist-info/WHEEL
cgutils-0.1.4.dist-info/entry_points.txt
cgutils-0.1.4.dist-info/metadata.json
cgutils-0.1.4.dist-info/top_level.txt
