Metadata-Version: 2.0
Name: cgutils
Version: 0.1.4
Summary: CLI for common tasks
Home-page: http://github.com//cgutils.git
Author: Dan Bradham
Author-email: danielbradham@gmail.com
License: MIT
Platform: UNKNOWN
Classifier: Development Status :: 3 - Alpha
Classifier: Intended Audience :: Developers
Classifier: License :: OSI Approved :: MIT License
Classifier: Natural Language :: English
Classifier: Operating System :: OS Independent
Classifier: Programming Language :: Python
Classifier: Programming Language :: Python :: 2
Requires-Dist: click
